FH/__init__.py
FH/dataset.py
FH/version.py
FantasticHelpers-0.0.1.dist-info/LICENSE
FantasticHelpers-0.0.1.dist-info/METADATA
FantasticHelpers-0.0.1.dist-info/WHEEL
FantasticHelpers-0.0.1.dist-info/top_level.txt
FantasticHelpers-0.0.1.dist-info/RECORD
